[
    {
        "name": "json grandson 1",
        "parentage": {
            "name": "json daughter 1",
            "father": {
                "name": "json father 1"
            },
            "mother": {
                "name": "json mother 1"
            }
        }
    },
    {
        "name": "json grandson 2",
        "parentage": {
            "name": "json daughter 2",
            "father": {
                "name": "json father 2"
            },
            "mother": {
                "name": "json mother 2"
            }
        }
    },
    {
        "name": "json grandson 3",
        "parentage": {
            "name": "json daughter 3",
            "father": {
                "name": "json father 2"
            },
            "mother": {
                "name": "json mother 2"
            }
        }
    }
]
